neurodynex/__init__.py
neurodynex/quick_test.py
neurodynex/adex_model/AdEx.py
neurodynex/adex_model/__init__.py
neurodynex/brunel_model/LIF_spiking_network.py
neurodynex/brunel_model/__init__.py
neurodynex/cable_equation/__init__.py
neurodynex/cable_equation/passive_cable.py
neurodynex/competing_populations/__init__.py
neurodynex/competing_populations/decision_making.py
neurodynex/data/alphabet.pickle.gz
neurodynex/exponential_integrate_fire/__init__.py
neurodynex/exponential_integrate_fire/exp_IF.py
neurodynex/hodgkin_huxley/HH.py
neurodynex/hodgkin_huxley/__init__.py
neurodynex/hopfield_network/__init__.py
neurodynex/hopfield_network/demo.py
neurodynex/hopfield_network/network.py
neurodynex/hopfield_network/pattern_tools.py
neurodynex/hopfield_network/plot_tools.py
neurodynex/leaky_integrate_and_fire/LIF.py
neurodynex/leaky_integrate_and_fire/__init__.py
neurodynex/neuron_type/__init__.py
neurodynex/neuron_type/neurons.py
neurodynex/ojas_rule/__init__.py
neurodynex/ojas_rule/oja.py
neurodynex/phase_plane_analysis/__init__.py
neurodynex/phase_plane_analysis/fitzhugh_nagumo.py
neurodynex/test/__init__.py
neurodynex/test/test_AdEx.py
neurodynex/test/test_HH.py
neurodynex/test/test_LIF.py
neurodynex/test/test_LIF_spiking_network.py
neurodynex/test/test_cable_equation.py
neurodynex/test/test_decision_making.py
neurodynex/test/test_exponential_IF.py
neurodynex/test/test_hopfield.py
neurodynex/test/test_nagumo.py
neurodynex/test/test_neuron_type.py
neurodynex/test/test_oja.py
neurodynex/test/test_spike_tools.py
neurodynex/test/test_working_memory.py
neurodynex/tools/__init__.py
neurodynex/tools/input_factory.py
neurodynex/tools/plot_tools.py
neurodynex/tools/spike_tools.py
neurodynex/working_memory_network/__init__.py
neurodynex/working_memory_network/wm_model.py
neurodynex-0.3.4.dist-info/DESCRIPTION.rst
neurodynex-0.3.4.dist-info/METADATA
neurodynex-0.3.4.dist-info/RECORD
neurodynex-0.3.4.dist-info/WHEEL
neurodynex-0.3.4.dist-info/metadata.json
neurodynex-0.3.4.dist-info/top_level.txt
