Metadata-Version: 2.0
Name: neurodynex
Version: 0.3.4
Summary: Python exercises accompanying the book Neuronal Dynamics by Wulfram Gerstner, Werner M. Kistler, Richard Naud and Liam Paninski.
Home-page: https://github.com/EPFL-LCN/neuronaldynamics-exercises
Author: LCN-EPFL
Author-email: alex.seeholzer@epfl.ch
License: GPLv2
Keywords: compneuro,science,teaching,neuroscience,brian
Platform: UNKNOWN
Classifier: Development Status :: 3 - Alpha
Classifier: License :: OSI Approved :: GNU General Public License v2 (GPLv2)
Classifier: Programming Language :: Python :: 2.7
Classifier: Programming Language :: Python :: 3.4
Classifier: Topic :: Scientific/Engineering :: Medical Science Apps.
Requires-Dist: brian2 (>=2.0)
Requires-Dist: matplotlib
Requires-Dist: numpy
Requires-Dist: scipy
